penaltymodel/__init__.py
penaltymodel/cache/__init__.py
penaltymodel/cache/cache_manager.py
penaltymodel/cache/database_manager.py
penaltymodel/cache/interface.py
penaltymodel/cache/package_info.py
penaltymodel/cache/schema.py
penaltymodel/cache/utils.py
penaltymodel_cache-0.4.5.dist-info/METADATA
penaltymodel_cache-0.4.5.dist-info/WHEEL
penaltymodel_cache-0.4.5.dist-info/entry_points.txt
penaltymodel_cache-0.4.5.dist-info/top_level.txt
penaltymodel_cache-0.4.5.dist-info/RECORD
