Metadata-Version: 2.1
Name: penaltymodel-cache
Version: 0.4.5
Summary: A local cache for penalty models.
Home-page: https://github.com/dwavesystems/penaltymodel
Author: D-Wave Systems Inc.
Author-email: acondello@dwavesys.com
License: Apache 2.0
Platform: UNKNOWN
Classifier: License :: OSI Approved :: Apache Software License
Classifier: Operating System :: MacOS :: MacOS X
Classifier: Operating System :: Microsoft :: Windows
Classifier: Operating System :: POSIX :: Linux
Classifier: Programming Language :: Python :: 3
Classifier: Programming Language :: Python :: 3.6
Classifier: Programming Language :: Python :: 3.7
Classifier: Programming Language :: Python :: 3.8
Classifier: Programming Language :: Python :: 3.9
Classifier: Programming Language :: Python :: 3.10
Requires-Python: >=3.6
Requires-Dist: penaltymodel (<0.17.0,>=0.16.0)
Requires-Dist: homebase (<2.0.0,>=1.0.0)
Requires-Dist: dimod (<0.11.0,>=0.8.0)
